vlrscraper/__init__.py
vlrscraper/constants.py
vlrscraper/controllers.py
vlrscraper/logger.py
vlrscraper/resource.py
vlrscraper/resources.py
vlrscraper/scraping.py
vlrscraper/utils.py
vlrscraper/vlr_resources.py
vlrscraper-0.0.4.dist-info/METADATA
vlrscraper-0.0.4.dist-info/WHEEL
vlrscraper-0.0.4.dist-info/top_level.txt
vlrscraper-0.0.4.dist-info/RECORD
