Metadata-Version: 2.2
Name: vlrscraper
Version: 0.0.4
Summary: vlrscraper - Scrape data from vlr seamlessly
Author-email: Joe Paton <joantpat@gmail.com>
Requires-Python: >=3.6
Requires-Dist: lxml
Requires-Dist: lxml-stubs
Requires-Dist: requests
Requires-Dist: types-requests
Provides-Extra: dev
Requires-Dist: tox; extra == "dev"
Requires-Dist: pytest; extra == "dev"
Requires-Dist: pytest-cov; extra == "dev"
Requires-Dist: ruff; extra == "dev"
Requires-Dist: pyright; extra == "dev"
Requires-Dist: sphinx; extra == "dev"
Provides-Extra: test
Requires-Dist: pytest; extra == "test"
Requires-Dist: pytest-cov; extra == "test"
Provides-Extra: lint
Requires-Dist: ruff; extra == "lint"
Requires-Dist: pyright; extra == "lint"
Provides-Extra: docs
Requires-Dist: sphinx; extra == "docs"
